pygame_setup/__init__.py
pygame_setup/main.py
pygame_setup/utils.py
pygame_setup-1.0.1.dist-info/licenses/LICENSE
pygame_setup-1.0.1.dist-info/METADATA
pygame_setup-1.0.1.dist-info/WHEEL
pygame_setup-1.0.1.dist-info/entry_points.txt
pygame_setup-1.0.1.dist-info/top_level.txt
pygame_setup-1.0.1.dist-info/RECORD
