Metadata-Version: 2.4
Name: pygame-setup
Version: 1.0.1
Summary: A tool for quickly setting up pygame projects.
Requires-Python: >=3.7
License-File: LICENSE
Requires-Dist: inquirer
Dynamic: license-file
